{
  "schemaVersion": 1,
  "decks": [
    {
      "id": "recommend-201604-1",
      "name": "《太陽竜》デッキ",
      "flag": "dragon-world",
      "buddy": "bf-d-bt01-0022",
      "recipe": [
        [
          "bf-d-bt01-0002",
          4
        ],
        [
          "bf-d-bt01-0001",
          4
        ],
        [
          "bf-d-bt01-0022",
          4
        ],
        [
          "bf-d-bt01-0009",
          2
        ],
        [
          "bf-d-bt01-0023",
          4
        ],
        [
          "bf-d-cr-0006",
          4
        ],
        [
          "bf-d-bt01-0010",
          4
        ],
        [
          "bf-d-sd01-0005",
          4
        ],
        [
          "bf-h-ss01-0011",
          4
        ],
        [
          "bf-d-sd01-0014",
          4
        ],
        [
          "bf-d-sd01-0013",
          2
        ],
        [
          "bf-d-bt01-0091",
          2
        ],
        [
          "bf-d-bt01-0024",
          2
        ],
        [
          "bf-d-bt01-0026",
          4
        ],
        [
          "bf-d-sd01-0015",
          2
        ]
      ]
    },
    {
      "id": "recommend-201604-2",
      "name": "《黒竜》デッキ",
      "flag": "darkness-dragon-world",
      "buddy": "bf-d-bt01-0039",
      "recipe": [
        [
          "bf-d-bt01-0006",
          4
        ],
        [
          "bf-d-bt01-0005",
          4
        ],
        [
          "bf-d-sd03-0004",
          4
        ],
        [
          "bf-d-bt01-0068",
          2
        ],
        [
          "bf-d-bt01-0039",
          4
        ],
        [
          "bf-d-bt01-0015",
          4
        ],
        [
          "bf-d-sd03-0007",
          2
        ],
        [
          "bf-d-bt01-0069",
          2
        ],
        [
          "bf-d-sd03-0005",
          2
        ],
        [
          "bt04-0101",
          4
        ],
        [
          "td06-0015",
          4
        ],
        [
          "bf-d-sd03-0011",
          3
        ],
        [
          "bf-d-bt01-0016",
          3
        ],
        [
          "bf-d-bt01-0042",
          4
        ],
        [
          "bf-d-sd03-0015",
          4
        ]
      ]
    },
    {
      "id": "recommend-201604-3",
      "name": "スタードラゴンデッキ",
      "flag": "star-dragon-world",
      "buddy": "bf-d-bt01-0044",
      "recipe": [
        [
          "bf-d-bt01-0008",
          4
        ],
        [
          "bf-d-bt01-0044",
          4
        ],
        [
          "bf-h-bt02-0008",
          4
        ],
        [
          "bf-d-bt01-0076",
          4
        ],
        [
          "bf-d-bt01-0018",
          4
        ],
        [
          "bf-d-sd02-0008",
          2
        ],
        [
          "bf-d-sd02-0007",
          2
        ],
        [
          "bf-h-bt04-0041",
          2
        ],
        [
          "bf-h-bt04-0019",
          2
        ],
        [
          "bf-d-sd02-0014",
          4
        ],
        [
          "bf-d-bt01-0048",
          4
        ],
        [
          "bf-d-bt01-0019",
          3
        ],
        [
          "bf-d-bt01-0121",
          3
        ],
        [
          "bf-d-bt01-0047",
          2
        ],
        [
          "bf-d-bt01-0049",
          4
        ],
        [
          "bf-h-bt04-0020",
          2
        ]
      ]
    },
    {
      "id": "recommend-201604-4",
      "name": "アスモダイデッキ",
      "flag": "magic-world",
      "buddy": "bf-d-bt01-0004",
      "recipe": [
        [
          "bf-d-bt01-0013",
          2
        ],
        [
          "bf-d-bt01-0004",
          4
        ],
        [
          "td07-0002",
          4
        ],
        [
          "bf-d-bt01-0031",
          4
        ],
        [
          "bf-h-eb04-0002",
          4
        ],
        [
          "bf-d-bt01-0100",
          2
        ],
        [
          "bt05-0015",
          2
        ],
        [
          "bf-h-pp01-0012",
          2
        ],
        [
          "td07-0012",
          4
        ],
        [
          "bf-h-bt03-0030",
          4
        ],
        [
          "bf-d-bt01-0036",
          4
        ],
        [
          "bf-d-bt01-0107",
          2
        ],
        [
          "bf-d-bt01-0105",
          2
        ],
        [
          "td07-0011",
          2
        ],
        [
          "bf-h-pp01-0024",
          2
        ],
        [
          "bf-d-bt01-0064",
          2
        ],
        [
          "bf-d-bt01-0103",
          2
        ],
        [
          "bf-d-bt01-0067",
          2
        ]
      ]
    },
    {
      "id": "recommend-201604-5",
      "name": "《シャドウシェイド》デッキ",
      "flag": "magic-world",
      "buddy": "bf-d-bt01-0012",
      "recipe": [
        [
          "bf-d-bt01-0003",
          4
        ],
        [
          "bf-d-bt01-0012",
          4
        ],
        [
          "bf-d-bt01-0060",
          2
        ],
        [
          "bf-d-bt01-0032",
          4
        ],
        [
          "bf-d-bt01-0101",
          4
        ],
        [
          "bf-d-bt01-0063",
          4
        ],
        [
          "bf-d-bt01-0034",
          4
        ],
        [
          "td07-0012",
          4
        ],
        [
          "bf-h-bt03-0015",
          4
        ],
        [
          "bf-d-bt01-0102",
          4
        ],
        [
          "bf-d-bt01-0036",
          3
        ],
        [
          "bf-h-bt03-0060",
          2
        ],
        [
          "bt01-0088",
          2
        ],
        [
          "bf-d-bt01-0103",
          2
        ],
        [
          "bf-d-bt01-0037",
          3
        ]
      ]
    }
  ]
}
